pyshare/__init__.py
pyshare/share.py
pyshare_lib-0.0.3.dist-info/LICENSE.md
pyshare_lib-0.0.3.dist-info/METADATA
pyshare_lib-0.0.3.dist-info/WHEEL
pyshare_lib-0.0.3.dist-info/top_level.txt
pyshare_lib-0.0.3.dist-info/RECORD
