Metadata-Version: 2.1
Name: pyshare-lib
Version: 0.0.3
Summary: PyShare - A Python Sharing library for DataFrames
Author-email: Guen Prawiroatmodjo <hi@guen.pw>
Project-URL: Homepage, https://github.com/guenp/pyshare
Project-URL: Issues, https://github.com/guenp/pyshare/issues
Classifier: Programming Language :: Python :: 3
Classifier: License :: OSI Approved :: MIT License
Classifier: Operating System :: OS Independent
Requires-Python: >=3.8
License-File: LICENSE.md
